{
    "kit": {
      "config": {
        "type": "KIT",
        "source": "MASTER_LIST",
        "defaultValues": true,
        "createdAt": "2025-08-13T00:00:00.000Z",
        "updatedAt": "2025-08-13T00:00:00.000Z"
      },
      "categories": [
        { "id": "kit_cat_user", "displayName": "Custom", "isPredefined": true, "iconName": "UserIcon", "show": true },
        { "id": "kit_cat_camera_bodies", "displayName": "Camera Bodies", "isPredefined": true, "iconName": "CameraIcon", "show": true },
        { "id": "kit_cat_lenses", "displayName": "Lenses", "isPredefined": true, "iconName": "LensIcon", "show": true },
        { "id": "kit_cat_lighting", "displayName": "Lighting", "isPredefined": true, "iconName": "FlashIcon", "show": true },
        { "id": "kit_cat_power", "displayName": "Power", "isPredefined": true, "iconName": "BatteryIcon", "show": true },
        { "id": "kit_cat_media", "displayName": "Memory Cards", "isPredefined": true, "iconName": "MemoryCardIcon", "show": true },
        { "id": "kit_cat_support", "displayName": "Support Gear", "isPredefined": true, "iconName": "TripodIcon", "show": true },
        { "id": "kit_cat_bags", "displayName": "Bags & Cases", "isPredefined": true, "iconName": "BagIcon", "show": true },
        { "id": "kit_cat_data_management", "displayName": "Data Management", "isPredefined": true, "iconName": "LaptopIcon", "show": true },
        { "id": "kit_cat_documents", "displayName": "Documents", "isPredefined": true, "iconName": "DocumentsIcon", "show": true },
        { "id": "kit_cat_essentials", "displayName": "Day Essentials", "isPredefined": true, "iconName": "EssentialsIcon", "show": true }
      ],
      "items": [
        { "id": "ktcam01", "name": "Primary Camera Body", "categoryId": "kit_cat_camera_bodies", "checked": false, "notes": "", "quantity": 1, "isPredefined": true },
        { "id": "ktcam02", "name": "Backup Camera Body", "categoryId": "kit_cat_camera_bodies", "checked": false, "notes": "", "quantity": 1, "isPredefined": true },
        { "id": "ktlen01", "name": "Wide-Angle Lens", "categoryId": "kit_cat_lenses", "notes": "e.g., 24mm or 35mm", "checked": false, "quantity": 1, "isPredefined": true },
        { "id": "ktlen02", "name": "Standard Zoom Lens", "categoryId": "kit_cat_lenses", "notes": "e.g., 24-70mm", "checked": false, "quantity": 1, "isPredefined": true },
        { "id": "ktlen03", "name": "Telephoto Lens", "categoryId": "kit_cat_lenses", "notes": "e.g., 70-200mm", "checked": false, "quantity": 1, "isPredefined": true },
        { "id": "ktlen04", "name": "Prime/Portrait Lens", "categoryId": "kit_cat_lenses", "notes": "e.g., 50mm or 85mm", "checked": false, "quantity": 1, "isPredefined": true },
        { "id": "ktlen05", "name": "Macro Lens", "categoryId": "kit_cat_lenses", "notes": "For ring shots", "checked": false, "quantity": 1, "isPredefined": true },
        { "id": "ktlt01", "name": "On-Camera Flash (Speedlite)", "categoryId": "kit_cat_lighting", "checked": false, "notes": "", "quantity": 2, "isPredefined": true },
        { "id": "ktlt02", "name": "External Flash (Speedlite)", "categoryId": "kit_cat_lighting", "checked": false, "notes": "", "quantity": 1, "isPredefined": true },
        { "id": "ktlt03", "name": "Continuous Lighting (Ring Light)", "categoryId": "kit_cat_lighting", "checked": false, "notes": "", "quantity": 1, "isPredefined": true },
        { "id": "ktlt04", "name": "Ring Light", "categoryId": "kit_cat_lighting", "checked": false, "notes": "", "quantity": 1, "isPredefined": true },
        { "id": "ktpw01", "name": "Camera Batteries", "categoryId": "kit_cat_power", "checked": false, "notes": "", "quantity": 4, "isPredefined": true },
        { "id": "ktpw02", "name": "Flash Batteries (AA)", "categoryId": "kit_cat_power", "checked": false, "notes": "", "quantity": 16, "isPredefined": true },
        { "id": "ktpw03", "name": "Strobe Battery Packs", "categoryId": "kit_cat_power", "checked": false, "notes": "", "quantity": 2, "isPredefined": true },
        { "id": "ktpw04", "name": "Battery Chargers", "categoryId": "kit_cat_power", "checked": false, "notes": "", "quantity": 3, "isPredefined": true },
        { "id": "ktpw05", "name": "Portable Power Bank", "categoryId": "kit_cat_power", "checked": false, "notes": "", "quantity": 1, "isPredefined": true },
        { "id": "ktmem01", "name": "Primary Memory Cards (High Capacity)", "categoryId": "kit_cat_media", "checked": false, "notes": "", "quantity": 4, "isPredefined": true },
        { "id": "ktmem02", "name": "Backup Memory Cards", "categoryId": "kit_cat_media", "checked": false, "notes": "", "quantity": 4, "isPredefined": true },
        { "id": "ktmem03", "name": "Memory Card Holder/Case", "categoryId": "kit_cat_media", "checked": false, "notes": "", "quantity": 1, "isPredefined": true },
        { "id": "ktsup01", "name": "Tripod / Monopod", "categoryId": "kit_cat_support", "checked": false, "notes": "", "quantity": 1, "isPredefined": true },
        { "id": "ktsup02", "name": "Camera Straps/Harness", "categoryId": "kit_cat_support", "checked": false, "notes": "", "quantity": 1, "isPredefined": true },
        { "id": "ktbag01", "name": "Main Camera Bag (Roller or Backpack)", "categoryId": "kit_cat_bags", "checked": false, "notes": "", "quantity": 1, "isPredefined": true },
        { "id": "ktbag02", "name": "Light Stand Bag", "categoryId": "kit_cat_bags", "checked": false, "notes": "", "quantity": 1, "isPredefined": true },
        { "id": "ktdat01", "name": "Laptop or Tablet", "categoryId": "kit_cat_data_management", "checked": false, "notes": "", "quantity": 1, "isPredefined": true },
        { "id": "ktdat02", "name": "Portable SSD/Hard Drive", "categoryId": "kit_cat_data_management", "notes": "For on-site backup", "checked": false, "quantity": 1, "isPredefined": true },
        { "id": "ktdat03", "name": "Card Reader", "categoryId": "kit_cat_data_management", "checked": false, "notes": "", "quantity": 1, "isPredefined": true },
        { "id": "ktdoc01", "name": "Printed Timeline & Shot List", "categoryId": "kit_cat_documents", "checked": false, "notes": "", "quantity": 1, "isPredefined": true },
        { "id": "ktdoc02", "name": "Contact Sheet (Couple, Vendors)", "categoryId": "kit_cat_documents", "checked": false, "notes": "", "quantity": 1, "isPredefined": true },
        { "id": "ktdoc03", "name": "Copy of Contract & Insurance", "categoryId": "kit_cat_documents", "checked": false, "notes": "", "quantity": 1, "isPredefined": true },
        { "id": "ktes01", "name": "Comfortable Shoes", "categoryId": "kit_cat_essentials", "checked": false, "notes": "", "quantity": 1, "isPredefined": true },
        { "id": "ktes02", "name": "Water Bottle & Snacks", "categoryId": "kit_cat_essentials", "checked": false, "notes": "", "quantity": 1, "isPredefined": true },
        { "id": "ktes03", "name": "Painkillers & Plasters", "categoryId": "kit_cat_essentials", "checked": false, "notes": "", "quantity": 1, "isPredefined": true },
        { "id": "ktes04", "name": "Business Cards", "categoryId": "kit_cat_essentials", "checked": false, "notes": "", "quantity": 20, "isPredefined": true },
        { "id": "ktes05", "name": "Rain Cover for Bag/Camera", "categoryId": "kit_cat_essentials", "checked": false, "notes": "", "quantity": 1,  "isPredefined": true }
      ]
    },
    "coupleShots": {
      "config": {
        "type": "COUPLE_SHOTS",
        "source": "MASTER_LIST",
        "defaultValues": true,        
        "createdAt": "2025-08-13T00:00:00.000Z",
        "updatedAt": "2025-08-13T00:00:00.000Z"
      },
      "categories": [
          { "id": "couple_shot_cat_user", "displayName": "Custom", "isPredefined": true, "iconName": "UserIcon", "show": true },
          { "id": "couple_shot_cat_getting_ready", "displayName": "Getting Ready", "isPredefined": true, "iconName": "GettingReadyIcon", "show": true },
          { "id": "couple_shot_cat_first_look", "displayName": "First Look", "isPredefined": true, "iconName": "FirstLookIcon", "show": true },
          { "id": "couple_shot_cat_portraits", "displayName": "Couple Portraits", "isPredefined": true, "iconName": "PortraitsIcon", "show": true },
          { "id": "couple_shot_cat_ceremony", "displayName": "Ceremony", "isPredefined": true, "iconName": "CeremonyIcon", "show": true },
          { "id": "couple_shot_cat_golden_hour", "displayName": "Golden Hour / Sunset", "isPredefined": true, "iconName": "GoldenHourIcon", "show": true },
          { "id": "couple_shot_cat_reception", "displayName": "Reception", "isPredefined": true, "iconName": "ReceptionIcon", "show": true }
      ],
      "items": [
          { "id": "csgr01", "name": "P1 reads letter", "categoryId": "couple_shot_cat_getting_ready", "checked": false, "notes": "Capture Partner 1 reading letter from Partner 2", "isPredefined": true, "time": 3 },
          { "id": "csgr02", "name": "P2 reads letter", "categoryId": "couple_shot_cat_getting_ready", "checked": false, "notes": "Capture Partner 2 reading letter from Partner 1", "isPredefined": true, "time": 3 },
          { "id": "csgr03", "name": "Partner portraits", "categoryId": "couple_shot_cat_getting_ready", "checked": false, "notes": "Take solo portraits of each partner in full attire", "isPredefined": true, "time": 3 },
          { "id": "csgr04", "name": "Detail shots", "categoryId": "couple_shot_cat_getting_ready", "checked": false, "notes": "Photograph rings, vows, and other key items", "isPredefined": true, "time": 3 },
          { "id": "csfl01", "name": "Behind approach", "categoryId": "couple_shot_cat_first_look", "checked": false, "notes": "Capture Partner 1 walking up unseen from behind", "isPredefined": true, "time": 3 },
          { "id": "csfl02", "name": "Shoulder tap", "categoryId": "couple_shot_cat_first_look", "checked": false, "notes": "Photograph the moment of the tap before the turn", "isPredefined": true, "time": 3 },
          { "id": "csfl03", "name": "Reaction shot", "categoryId": "couple_shot_cat_first_look", "checked": false, "notes": "Get both partners emotional first reactions", "isPredefined": true, "time": 3 },
          { "id": "csfl04", "name": "Hug Embrace", "categoryId": "couple_shot_cat_first_look", "checked": false, "notes": "Shoot genuine hugs and joyful post-reveal emotion", "isPredefined": true, "time": 3 },
          { "id": "csfl05", "name": "Quiet moment", "categoryId": "couple_shot_cat_first_look", "checked": false, "notes": "Document a calm, intimate moment right after", "isPredefined": true, "time": 3 },
          { "id": "csp01", "name": "Classic portrait", "categoryId": "couple_shot_cat_portraits", "checked": false, "notes": "Couple looking at camera, posed and composed", "isPredefined": true, "time": 3 },
          { "id": "csp02", "name": "Romantic look", "categoryId": "couple_shot_cat_portraits", "checked": false, "notes": "Partners gazing at each other lovingly", "isPredefined": true, "time": 3 },
          { "id": "csp03", "name": "Walking shots", "categoryId": "couple_shot_cat_portraits", "checked": false, "notes": "Hand-in-hand walking toward and away from lens", "isPredefined": true, "time": 3 },
          { "id": "csp04", "name": "Almost kiss", "categoryId": "couple_shot_cat_portraits", "checked": false, "notes": "A tender moment just before the kiss", "isPredefined": true, "time": 3 },
          { "id": "csp05", "name": "Forehead kiss", "categoryId": "couple_shot_cat_portraits", "checked": false, "notes": "One partner kissing the others forehead", "isPredefined": true, "time": 3 },
          { "id": "csp06", "name": "Candid laughter", "categoryId": "couple_shot_cat_portraits", "checked": false, "notes": "Capture natural, joyful moments of laughter", "isPredefined": true, "time": 3 },
          { "id": "csp07", "name": "Lift or dip", "categoryId": "couple_shot_cat_portraits", "checked": false, "notes": "One partner lifts or dips the other playfully", "isPredefined": true, "time": 3 },
          { "id": "csp08", "name": "Hands close-up", "categoryId": "couple_shot_cat_portraits", "checked": false, "notes": "Focus on intertwined hands and wedding rings", "isPredefined": true, "time": 3 },
          { "id": "csp09", "name": "Wide scenic shot", "categoryId": "couple_shot_cat_portraits", "checked": false, "notes": "Couple small in frame with a dramatic backdrop", "isPredefined": true, "time": 3 },
          { "id": "csc01", "name": "Giving away", "categoryId": "couple_shot_cat_ceremony", "checked": false, "notes": "Capture the handoff moment during the ceremony", "isPredefined": true, "time": 3 },
          { "id": "csc02", "name": "Vow exchange", "categoryId": "couple_shot_cat_ceremony", "checked": false, "notes": "Photograph both partners reading their vows", "isPredefined": true, "time": 3 },
          { "id": "csc03", "name": "Ring exchange", "categoryId": "couple_shot_cat_ceremony", "checked": false, "notes": "Close-up of each partner placing the rings", "isPredefined": true, "time": 3 },
          { "id": "csc04", "name": "First kiss", "categoryId": "couple_shot_cat_ceremony", "checked": false, "notes": "Capture the first kiss as newlyweds", "isPredefined": true, "time": 3 },
          { "id": "csc05", "name": "Sign register", "categoryId": "couple_shot_cat_ceremony", "checked": false, "notes": "Get a clear shot of the couple signing papers", "isPredefined": true, "time": 3 },
          { "id": "csc06", "name": "Recessional", "categoryId": "couple_shot_cat_ceremony", "checked": false, "notes": "Couple walking joyfully back down the aisle", "isPredefined": true, "time": 3 },
          { "id": "csc07", "name": "Confetti toss", "categoryId": "couple_shot_cat_ceremony", "checked": false, "notes": "Guests showering the couple with confetti", "isPredefined": true, "time": 3 },
          { "id": "csgh01", "name": "Sunset silhouette", "categoryId": "couple_shot_cat_golden_hour", "checked": false, "notes": "Couple outline framed by the glowing sunset", "isPredefined": true, "time": 3 },
          { "id": "csgh02", "name": "Backlit halo shot", "categoryId": "couple_shot_cat_golden_hour", "checked": false, "notes": "Warm sunlight creates a soft glow around couple", "isPredefined": true, "time": 3 },
          { "id": "csgh03", "name": "Walk into sunset", "categoryId": "couple_shot_cat_golden_hour", "checked": false, "notes": "Couple walking away into the glowing horizon", "isPredefined": true, "time": 3 },
          { "id": "csgh04", "name": "Sunset embrace", "categoryId": "couple_shot_cat_golden_hour", "checked": false, "notes": "Intimate hug bathed in golden hour light", "isPredefined": true, "time": 3 },
          { "id": "csr01", "name": "Grand entrance", "categoryId": "couple_shot_cat_reception", "checked": false, "notes": "Capture couples entrance into the reception", "isPredefined": true, "time": 3 },
          { "id": "csr02", "name": "Cutting cake", "categoryId": "couple_shot_cat_reception", "checked": false, "notes": "Photograph the cake-cutting and reactions", "isPredefined": true, "time": 3 },
          { "id": "csr03", "name": "First dance", "categoryId": "couple_shot_cat_reception", "checked": false, "notes": "Shoot the couples first dance together", "isPredefined": true, "time": 3 },
          { "id": "csr04", "name": "Speech candids", "categoryId": "couple_shot_cat_reception", "checked": false, "notes": "Candid shots of reactions during speeches", "isPredefined": true, "time": 3 },
          { "id": "csr05", "name": "Quiet moment", "categoryId": "couple_shot_cat_reception", "checked": false, "notes": "Capture the couple alone amid the celebration", "isPredefined": true, "time": 3 },
          { "id": "csr06", "name": "End-of-night shot", "categoryId": "couple_shot_cat_reception", "checked": false, "notes": "Creative final photo, like sparklers or exit", "isPredefined": true, "time": 3 }
      ]
    },
    "groupShots": {
      "config": {
          "type": "GROUP_SHOTS",
          "source": "MASTER_LIST",
          "defaultValues": true,          
          "createdAt": "2025-08-13T00:00:00.000Z",
          "updatedAt": "2025-08-13T00:00:00.000Z"
      },
      "categories": [
          { "id": "group_shot_cat_user", "displayName": "Custom", "isPredefined": true, "iconName": "UserIcon", "show": true },
          { "id": "group_shot_cat_family", "displayName": "Family", "isPredefined": true, "iconName": "FamilyIcon", "show": true },
          { "id": "group_shot_cat_wedding_party", "displayName": "Wedding Party", "isPredefined": true, "iconName": "WeddingPartyIcon", "show": true },
          { "id": "group_shot_cat_extended_family", "displayName": "Extended Family", "isPredefined": true, "iconName": "ExtendedFamilyIcon", "show": true },
          { "id": "group_shot_cat_friends", "displayName": "Friends", "isPredefined": true, "iconName": "FriendsIcon", "show": true },
          { "id": "group_shot_cat_others", "displayName": "Others", "isPredefined": true, "iconName": "OthersIcon", "show": true },
          { "id": "group_shot_cat_fun", "displayName": "Fun", "isPredefined": true, "iconName": "FunIcon", "show": true }
      ],
      "items": [
          { "id": "gsf01", "name": "P1 parents", "categoryId": "group_shot_cat_family", "checked": false, "notes": "Couple posed with Partner 1s parents", "isPredefined": true, "peopleIds": ["partner1_parent1", "partner1_parent2"], "time": 5 },
          { "id": "gsf02", "name": "P2 parents", "categoryId": "group_shot_cat_family", "checked": false, "notes": "Couple posed with Partner 2s parents", "isPredefined": true, "peopleIds": ["partner2_parent1", "partner2_parent2"], "time": 5 },
          { "id": "gsf03", "name": "All parents", "categoryId": "group_shot_cat_family", "checked": false, "notes": "Couple with both sets of parents together", "isPredefined": true, "peopleIds": ["partner1_parent1", "partner1_parent2", "partner2_parent1", "partner2_parent2"], "time": 5 },
          { "id": "gsf04", "name": "P1 immediate fam", "categoryId": "group_shot_cat_family", "checked": false, "notes": "Partner 1s parents and siblings with the couple", "isPredefined": true, "peopleIds": ["partner1_parent1", "partner1_parent2", "partner1_sibling1", "partner1_sibling2"], "time": 5 },
          { "id": "gsf05", "name": "P2 immediate fam", "categoryId": "group_shot_cat_family", "checked": false, "notes": "Partner 2s parents and siblings with the couple", "isPredefined": true, "peopleIds": ["partner2_parent1", "partner2_parent2", "partner2_sibling1", "partner2_sibling2"], "time": 5 },
          { "id": "gsf06", "name": "All immediate fam", "categoryId": "group_shot_cat_family", "checked": false, "notes": "Both families parents and siblings with couple", "isPredefined": true, "peopleIds": ["partner1_parent1", "partner1_parent2", "partner1_sibling1", "partner1_sibling2", "partner2_parent1", "partner2_parent2", "partner2_sibling1", "partner2_sibling2"], "time": 5 },
          { "id": "gsf07", "name": "All siblings", "categoryId": "group_shot_cat_family", "checked": false, "notes": "Couple with siblings from both families", "isPredefined": true, "peopleIds": ["partner1_sibling1", "partner1_sibling2", "partner2_sibling1", "partner2_sibling2"], "time": 5 },
          { "id": "gsf08", "name": "Grandparents", "categoryId": "group_shot_cat_family", "checked": false, "notes": "Couple with each side grandparents separately", "isPredefined": true, "peopleIds": ["partner1_grandparent1", "partner1_grandparent2", "partner2_grandparent1", "partner2_grandparent2"], "time": 5 },
          { "id": "gsf09", "name": "Generations shot", "categoryId": "group_shot_cat_family", "checked": false, "notes": "Include couple, parents, and grandparents in frame", "isPredefined": true, "peopleIds": ["partner1_grandparent1", "partner1_grandparent2", "partner2_grandparent1", "partner2_grandparent2", "partner1_parent1", "partner1_parent2", "partner2_parent1", "partner2_parent2"], "time": 5 },
          { "id": "gswp01", "name": "Full wedding party", "categoryId": "group_shot_cat_wedding_party", "checked": false, "notes": "Couple posed with entire wedding party together", "isPredefined": true, "peopleIds": ["partner1_maid1", "partner1_maid2", "partner1_bestman1", "partner1_bestman2", "partner2_maid1", "partner2_maid2", "partner2_bestman1", "partner2_bestman2"], "time": 5 },
          { "id": "gswp02", "name": "P1 attendants", "categoryId": "group_shot_cat_wedding_party", "checked": false, "notes": "Partner 1 with their bridesmaids or groomsmen", "isPredefined": true, "peopleIds": ["partner1_maid1", "partner1_maid2", "partner1_bestman1", "partner1_bestman2"], "time": 5 },
          { "id": "gswp03", "name": "P2 attendants", "categoryId": "group_shot_cat_wedding_party", "checked": false, "notes": "Partner 2 with their bridesmaids or groomsmen", "isPredefined": true, "peopleIds": ["partner2_maid1", "partner2_maid2", "partner2_bestman1", "partner2_bestman2"], "time": 5 },
          { "id": "gswp04", "name": "P1 & Maid/Best Man", "categoryId": "group_shot_cat_wedding_party", "checked": false, "notes": "Partner 1 with Maid of Honour or Partner 2 with Best Man", "isPredefined": true, "peopleIds": ["partner1_maid1", "partner1_maid2", "partner1_bestman1", "partner1_bestman2", "partner2_maid1", "partner2_maid2", "partner2_bestman1", "partner2_bestman2"], "time": 5 },
          { "id": "gswp05", "name": "All attendants", "categoryId": "group_shot_cat_wedding_party", "checked": false, "notes": "All bridesmaids and groomsmen grouped together", "isPredefined": true, "peopleIds": ["partner1_maid1", "partner1_maid2", "partner1_bestman1", "partner1_bestman2", "partner2_maid1", "partner2_maid2", "partner2_bestman1", "partner2_bestman2"], "time": 5 },
          { "id": "gswp06", "name": "Flower girls/ring bearers", "categoryId": "group_shot_cat_wedding_party", "checked": false, "notes": "Couple with flower girls and ring bearers posed", "isPredefined": true, "peopleIds": ["partner1_flower_girl1", "partner1_flower_girl2", "partner1_ring_bearer1", "partner1_ring_bearer2", "partner2_flower_girl1", "partner2_flower_girl2", "partner2_ring_bearer1", "partner2_ring_bearer2"], "time": 5 },
          { "id": "gswp07", "name": "Couple with ushers", "categoryId": "group_shot_cat_wedding_party", "checked": false, "notes": "Group shot with couple and their ushers", "isPredefined": true, "peopleIds": ["partner1_usher1", "partner1_usher2", "partner2_usher1", "partner2_usher2"], "time": 5 },
          { "id": "gsxf01", "name": "P1 extended family", "categoryId": "group_shot_cat_extended_family", "checked": false, "notes": "Couple posed with Partner 1s extended family", "isPredefined": true, "peopleIds": ["partner1_extended_family1", "partner1_extended_family2", "partner1_extended_family3", "partner1_extended_family4"], "time": 5 },
          { "id": "gsxf02", "name": "P2 extended family", "categoryId": "group_shot_cat_extended_family", "checked": false, "notes": "Couple posed with Partner 2s extended family", "isPredefined": true, "peopleIds": ["partner2_extended_family1", "partner2_extended_family2", "partner2_extended_family3", "partner2_extended_family4"], "time": 5 },
          { "id": "gsxf03", "name": "All aunts & uncles", "categoryId": "group_shot_cat_extended_family", "checked": false, "notes": "Couple with all aunts and uncles together", "isPredefined": true, "peopleIds": ["partner1_aunt1", "partner1_aunt2", "partner1_uncle1", "partner1_uncle2", "partner2_aunt1", "partner2_aunt2", "partner2_uncle1", "partner2_uncle2"], "time": 5 },
          { "id": "gsxf04", "name": "All cousins", "categoryId": "group_shot_cat_extended_family", "checked": false, "notes": "Group shot of couple with all cousins present", "isPredefined": true, "peopleIds": ["partner1_cousin1", "partner1_cousin2", "partner1_cousin3", "partner1_cousin4", "partner2_cousin1", "partner2_cousin2", "partner2_cousin3", "partner2_cousin4"], "time": 5 },
          { "id": "gsfr01", "name": "Close friends", "categoryId": "group_shot_cat_friends", "checked": false, "notes": "Couple posed with their closest friends", "isPredefined": true, "peopleIds": ["partner1_friend1", "partner1_friend2", "partner1_friend3", "partner1_friend4", "partner2_friend1", "partner2_friend2", "partner2_friend3", "partner2_friend4"], "time": 5 },
          { "id": "gsfr02", "name": "University friends", "categoryId": "group_shot_cat_friends", "checked": false, "notes": "Couple with friends from university or college", "isPredefined": true, "peopleIds": ["partner1_university_friend1", "partner1_university_friend2", "partner1_university_friend3", "partner1_university_friend4", "partner2_university_friend1", "partner2_university_friend2", "partner2_university_friend3", "partner2_university_friend4"], "time": 5 },
          { "id": "gsfr03", "name": "School friends", "categoryId": "group_shot_cat_friends", "checked": false, "notes": "Couple with friends from school days", "isPredefined": true, "peopleIds": ["partner1_school_friend1", "partner1_school_friend2", "partner1_school_friend3", "partner1_school_friend4", "partner2_school_friend1", "partner2_school_friend2", "partner2_school_friend3", "partner2_school_friend4"], "time": 5 },
          { "id": "gsfr04", "name": "Work friends", "categoryId": "group_shot_cat_friends", "checked": false, "notes": "Couple posed with colleagues and work friends", "isPredefined": true, "peopleIds": ["partner1_work_friend1", "partner1_work_friend2", "partner1_work_friend3", "partner1_work_friend4", "partner2_work_friend1", "partner2_work_friend2", "partner2_work_friend3", "partner2_work_friend4"], "time": 5 },
          { "id": "gsot01", "name": "Full guest group", "categoryId": "group_shot_cat_others", "checked": false, "notes": "Capture a wide shot with all wedding guests together", "isPredefined": true, "peopleIds": ["guest1", "guest2", "guest3", "guest4", "guest5", "guest6", "guest7", "guest8", "guest9", "guest10"], "time": 10 },
          { "id": "gsfu01", "name": "Party lifting couple", "categoryId": "group_shot_cat_fun", "checked": false, "notes": "Wedding party lifting the couple joyfully", "isPredefined": true, "peopleIds": ["partner1_maid1", "partner1_maid2", "partner1_bestman1", "partner1_bestman2", "partner2_maid1", "partner2_maid2", "partner2_bestman1", "partner2_bestman2"], "time": 5 },
          { "id": "gsfu02", "name": "Guest tunnel", "categoryId": "group_shot_cat_fun", "checked": false, "notes": "Guests forming a tunnel or archway for couple", "isPredefined": true, "peopleIds": ["guest1", "guest2", "guest3", "guest4", "guest5", "guest6", "guest7", "guest8", "guest9", "guest10"], "time": 5 },
          { "id": "gsfu03", "name": "Silly face shot", "categoryId": "group_shot_cat_fun", "checked": false, "notes": "Fun candid with wedding party making silly faces", "isPredefined": true, "peopleIds": ["partner1_maid1", "partner1_maid2", "partner1_bestman1", "partner1_bestman2", "partner2_maid1", "partner2_maid2", "partner2_bestman1", "partner2_bestman2"], "time": 5 },
          { "id": "gsfu04", "name": "Confetti toss", "categoryId": "group_shot_cat_fun", "checked": false, "notes": "Guests throwing confetti around the couple", "isPredefined": true, "peopleIds": ["guest1", "guest2", "guest3", "guest4", "guest5", "guest6", "guest7", "guest8", "guest9", "guest10"], "time": 5 },
          { "id": "gsfu05", "name": "Hobby group", "categoryId": "group_shot_cat_fun", "checked": false, "notes": "Couple with guests from a shared hobby or club", "isPredefined": true, "peopleIds": ["guest1", "guest2", "guest3", "guest4", "guest5", "guest6", "guest7", "guest8", "guest9", "guest10"], "time": 5 }
      ]
    },
    "tasks": {
      "config": {
          "type": "TASKS",
          "source": "MASTER_LIST",
          "defaultValues": true,
          "createdAt": "2025-08-13T00:00:00.000Z",
          "updatedAt": "2025-08-13T00:00:00.000Z"
      },
      "categories": [
          { "id": "task_cat_user", "displayName": "Custom", "isPredefined": true, "iconName": "UserIcon", "show": true },
          { "id": "task_cat_week_before", "displayName": "Week Before", "isPredefined": true, "iconName": "WeekBeforeIcon", "show": true },
          { "id": "task_cat_night_before", "displayName": "Night Before", "isPredefined": true, "iconName": "NightBeforeIcon", "show": true },
          { "id": "task_cat_morning_of", "displayName": "Morning Of", "isPredefined": true, "iconName": "MorningOfIcon", "show": true },
          { "id": "task_cat_after_wedding", "displayName": "After Wedding", "isPredefined": true, "iconName": "AfterWeddingIcon", "show": true }
      ],
      "items": [
          { "id": "tswk01", "name": "Confirm timeline", "categoryId": "task_cat_week_before", "checked": false, "notes": "Double-check details with couple and all vendors", "isPredefined": true },
          { "id": "tswk02", "name": "Vendor check-in", "categoryId": "task_cat_week_before", "checked": false, "notes": "Touch base with videographer and key vendors", "isPredefined": true },
          { "id": "tswk03", "name": "Print shot list", "categoryId": "task_cat_week_before", "checked": false, "notes": "Prepare and print final group photo checklist", "isPredefined": true },
          { "id": "tswk04", "name": "Check forecast", "categoryId": "task_cat_week_before", "checked": false, "notes": "Review long-range weather and make backup plans", "isPredefined": true },
          { "id": "tswk05", "name": "Confirm assistant", "categoryId": "task_cat_week_before", "checked": false, "notes": "Secure second shooter and send event brief", "isPredefined": true },
          { "id": "tsnb01", "name": "Charge batteries", "categoryId": "task_cat_night_before", "checked": false, "notes": "Include camera, flash, and trigger batteries", "isPredefined": true },
          { "id": "tsnb02", "name": "Format cards", "categoryId": "task_cat_night_before", "checked": false, "notes": "Clear all memory cards using in-camera format", "isPredefined": true },
          { "id": "tsnb03", "name": "Clean gear", "categoryId": "task_cat_night_before", "checked": false, "notes": "Wipe lenses, filters, and check sensors for dust", "isPredefined": true },
          { "id": "tsnb04", "name": "Sync camera times", "categoryId": "task_cat_night_before", "checked": false, "notes": "Ensure date and time match across all bodies", "isPredefined": true },
          { "id": "tsnb05", "name": "Pack camera bag", "categoryId": "task_cat_night_before", "checked": false, "notes": "Follow your checklist to pack all essentials", "isPredefined": true },
          { "id": "tsnb06", "name": "Review timeline", "categoryId": "task_cat_night_before", "checked": false, "notes": "Go over the shot list and key event timings", "isPredefined": true },
          { "id": "tsnb07", "name": "Download maps", "categoryId": "task_cat_night_before", "checked": false, "notes": "Get offline maps for all venues and backup routes", "isPredefined": true },
          { "id": "tsnb08", "name": "Pack food & drink", "categoryId": "task_cat_night_before", "checked": false, "notes": "Bring snacks, water, and light meals for the day", "isPredefined": true },
          { "id": "tsnb09", "name": "Lay out clothes", "categoryId": "task_cat_night_before", "checked": false, "notes": "Prepare outfit and comfy shoes for long hours", "isPredefined": true },
          { "id": "tsnb10", "name": "Set alarms", "categoryId": "task_cat_night_before", "checked": false, "notes": "Set multiple alarms to avoid oversleeping", "isPredefined": true },
          { "id": "tsmo01", "name": "Check weather/traffic", "categoryId": "task_cat_morning_of", "checked": false, "notes": "Review forecast and check live traffic updates", "isPredefined": true },
          { "id": "tsmo02", "name": "Eat & hydrate", "categoryId": "task_cat_morning_of", "checked": false, "notes": "Have a solid meal and drink plenty of water", "isPredefined": true },
          { "id": "tsmo03", "name": "Load gear in car", "categoryId": "task_cat_morning_of", "checked": false, "notes": "Ensure all packed gear is safely in the vehicle", "isPredefined": true },
          { "id": "tsmo04", "name": "Mental walkthrough", "categoryId": "task_cat_morning_of", "checked": false, "notes": "Visualize the day’s flow and key responsibilities", "isPredefined": true },
          { "id": "tsmo05", "name": "Leave early", "categoryId": "task_cat_morning_of", "checked": false, "notes": "Plan to arrive with extra time for any delays", "isPredefined": true },
          { "id": "tsmo06", "name": "Silence phone", "categoryId": "task_cat_morning_of", "checked": false, "notes": "Mute notifications before arriving at venue", "isPredefined": true },
          { "id": "tsaw01", "name": "Backup cards", "categoryId": "task_cat_after_wedding", "checked": false, "notes": "Immediately back up all memory cards (2-3 locations)", "isPredefined": true },
          { "id": "tsaw02", "name": "Verify backup", "categoryId": "task_cat_after_wedding", "checked": false, "notes": "Verify backup integrity before formatting cards", "isPredefined": true },
          { "id": "tsaw03", "name": "Sneak peek", "categoryId": "task_cat_after_wedding", "checked": false, "notes": "Send a sneak peek gallery to the couple (1-5 images)", "isPredefined": true },
          { "id": "tsaw04", "name": "Put batteries back on charge", "categoryId": "task_cat_after_wedding", "checked": false, "notes": "Ensure all batteries are back on charge", "isPredefined": true },
          { "id": "tsaw05", "name": "Clean gear", "categoryId": "task_cat_after_wedding", "checked": false, "notes": "Wipe lenses, filters, and check sensors for dust", "isPredefined": true }
      ]
    }
}
